odoo/addons/helpdesk_ticket_subtags/CHANGELOG.md
odoo/addons/helpdesk_ticket_subtags/README.rst
odoo/addons/helpdesk_ticket_subtags/__init__.py
odoo/addons/helpdesk_ticket_subtags/__manifest__.py
odoo/addons/helpdesk_ticket_subtags/i18n/ca_ES.po
odoo/addons/helpdesk_ticket_subtags/i18n/es.po
odoo/addons/helpdesk_ticket_subtags/models/__init__.py
odoo/addons/helpdesk_ticket_subtags/models/helpdesk_tag.py
odoo/addons/helpdesk_ticket_subtags/static/description/icon.png
odoo/addons/helpdesk_ticket_subtags/tests/__init__.py
odoo/addons/helpdesk_ticket_subtags/tests/test_subtags.py
odoo/addons/helpdesk_ticket_subtags/views/helpdesk_tag_view.xml
odoo_addon_helpdesk_ticket_subtags-16.0.1.0.0.dist-info/METADATA
odoo_addon_helpdesk_ticket_subtags-16.0.1.0.0.dist-info/WHEEL
odoo_addon_helpdesk_ticket_subtags-16.0.1.0.0.dist-info/top_level.txt
odoo_addon_helpdesk_ticket_subtags-16.0.1.0.0.dist-info/RECORD
